example_cli/__init__.py
example_cli/__main__.py
example_cli/openlibrary.py
example_cli/sunrise.py
example_cli-0.4.0.dist-info/entry_points.txt
example_cli-0.4.0.dist-info/WHEEL
example_cli-0.4.0.dist-info/METADATA
example_cli-0.4.0.dist-info/RECORD
