Metadata-Version: 2.1
Name: example-cli
Version: 0.4.0
Summary: 
Author: RincewindWizzard
Author-email: git@magierdinge.de
Requires-Python: >=3.8,<4.0
Classifier: Programming Language :: Python :: 3
Classifier: Programming Language :: Python :: 3.10
Classifier: Programming Language :: Python :: 3.8
Classifier: Programming Language :: Python :: 3.9
Requires-Dist: Gooey (>=1.0.8,<2.0.0)
Requires-Dist: aiohttp (>=3.8.1,<4.0.0)
